{
  "session_id": "do-junknet-home-1770642128450290514",
  "session_name": "phone-tmux-live-1770642400",
  "prefix": "do",
  "host": "junknet-home",
  "cwd": "/home/junknet/Desktop/do-ai",
  "command": "bash -lc echo STRESS_BEGIN; i=0; while true; do i=$((i+1)); echo LIVE_LINE_$i; sleep 0.05; done",
  "pid": 1980412,
  "state": "exited",
  "exit_code": 0,
  "started_at": 1770642128,
  "updated_at": 1770642255,
  "last_output_at": 1770642255,
  "last_text": "[exited]",
  "lock_file": "/home/junknet/Desktop/do-ai/.do-ai.lock",
  "online": false,
  "age_seconds": 2
}